{
  "id": "partager",
  "conjugators": [
    {
      "conjugations": [
        {
          "translations": [
            {
              "lang": "FR",
              "value": "a partagé"
            },
            {
              "lang": "DZ",
              "value": "9essmet"
            }
          ],
          "gender": "F",
          "possession": "OTHER",
          "singular": true
        },
        {
          "translations": [
            {
              "lang": "FR",
              "value": "a partagé"
            },
            {
              "lang": "DZ",
              "value": "9ssemna"
            }
          ],
          "gender": "X",
          "possession": "I",
          "singular": false
        },
        {
          "translations": [
            {
              "lang": "FR",
              "value": "ai partagé"
            },
            {
              "lang": "DZ",
              "value": "9ssemt"
            }
          ],
          "gender": "X",
          "possession": "I",
          "singular": true
        },
        {
          "translations": [
            {
              "lang": "FR",
              "value": "ont partagé"
            },
            {
              "lang": "DZ",
              "value": "9essmou"
            }
          ],
          "gender": "M",
          "possession": "OTHER",
          "singular": false
        },
        {
          "translations": [
            {
              "lang": "FR",
              "value": "as partagé"
            },
            {
              "lang": "DZ",
              "value": "9ssemti"
            }
          ],
          "gender": "F",
          "possession": "YOU",
          "singular": true
        },
        {
          "translations": [
            {
              "lang": "FR",
              "value": "a partagé"
            },
            {
              "lang": "DZ",
              "value": "9ssem"
            }
          ],
          "gender": "M",
          "possession": "OTHER",
          "singular": true
        },
        {
          "translations": [
            {
              "lang": "FR",
              "value": "as partagé"
            },
            {
              "lang": "DZ",
              "value": "9ssemt"
            }
          ],
          "gender": "X",
          "possession": "YOU",
          "singular": true
        },
        {
          "translations": [
            {
              "lang": "FR",
              "value": "avez partagé"
            },
            {
              "lang": "DZ",
              "value": "9ssemtou"
            }
          ],
          "gender": "X",
          "possession": "YOU",
          "singular": false
        },
        {
          "translations": [
            {
              "lang": "FR",
              "value": "ont partagé"
            },
            {
              "lang": "DZ",
              "value": "9essmou"
            }
          ],
          "gender": "F",
          "possession": "OTHER",
          "singular": false
        }
      ],
      "tense": "PAST"
    },
    {
      "conjugations": [
        {
          "translations": [
            {
              "lang": "FR",
              "value": "partage"
            },
            {
              "lang": "DZ",
              "value": "ne9essmou"
            }
          ],
          "gender": "X",
          "possession": "I",
          "singular": false
        },
        {
          "translations": [
            {
              "lang": "FR",
              "value": "partage"
            },
            {
              "lang": "DZ",
              "value": "ye9ssem"
            }
          ],
          "gender": "M",
          "possession": "OTHER",
          "singular": true
        },
        {
          "translations": [
            {
              "lang": "FR",
              "value": "partages"
            },
            {
              "lang": "DZ",
              "value": "te9ssem"
            }
          ],
          "gender": "X",
          "possession": "YOU",
          "singular": true
        },
        {
          "translations": [
            {
              "lang": "FR",
              "value": "partage"
            },
            {
              "lang": "DZ",
              "value": "te9ssem"
            }
          ],
          "gender": "F",
          "possession": "OTHER",
          "singular": true
        },
        {
          "translations": [
            {
              "lang": "FR",
              "value": "partagez"
            },
            {
              "lang": "DZ",
              "value": "te9essmou"
            }
          ],
          "gender": "X",
          "possession": "YOU",
          "singular": false
        },
        {
          "translations": [
            {
              "lang": "FR",
              "value": "partage"
            },
            {
              "lang": "DZ",
              "value": "ne9ssem"
            }
          ],
          "gender": "X",
          "possession": "I",
          "singular": true
        },
        {
          "translations": [
            {
              "lang": "FR",
              "value": "partages"
            },
            {
              "lang": "DZ",
              "value": "te9essmi"
            }
          ],
          "gender": "F",
          "possession": "YOU",
          "singular": true
        },
        {
          "translations": [
            {
              "lang": "FR",
              "value": "partagent"
            },
            {
              "lang": "DZ",
              "value": "ye9essmou"
            }
          ],
          "gender": "M",
          "possession": "OTHER",
          "singular": false
        },
        {
          "translations": [
            {
              "lang": "FR",
              "value": "partagent"
            },
            {
              "lang": "DZ",
              "value": "ye9essmou"
            }
          ],
          "gender": "F",
          "possession": "OTHER",
          "singular": false
        }
      ],
      "tense": "PRESENT"
    }
  ],
  "possible_questions": [
    "WHY",
    "HOW"
  ],
  "possible_complements": [
    "OBJECT"
  ],
  "verb_type": "ACTION",
  "indirect_complement": true,
  "object_only": true
}
