{
  "id": "penser",
  "conjugators": [
    {
      "conjugations": [
        {
          "translations": [
            {
              "lang": "FR",
              "value": "ont pensé"
            },
            {
              "lang": "DZ",
              "value": "khammou"
            }
          ],
          "gender": "M",
          "possession": "OTHER",
          "singular": false
        },
        {
          "translations": [
            {
              "lang": "FR",
              "value": "a pensé"
            },
            {
              "lang": "DZ",
              "value": "khamemna"
            }
          ],
          "gender": "X",
          "possession": "I",
          "singular": false
        },
        {
          "translations": [
            {
              "lang": "FR",
              "value": "ai pensé"
            },
            {
              "lang": "DZ",
              "value": "khamemt"
            }
          ],
          "gender": "X",
          "possession": "I",
          "singular": true
        },
        {
          "translations": [
            {
              "lang": "FR",
              "value": "a pensé"
            },
            {
              "lang": "DZ",
              "value": "khamem"
            }
          ],
          "gender": "M",
          "possession": "OTHER",
          "singular": true
        },
        {
          "translations": [
            {
              "lang": "FR",
              "value": "avez pensé"
            },
            {
              "lang": "DZ",
              "value": "khamemtou"
            }
          ],
          "gender": "X",
          "possession": "YOU",
          "singular": false
        },
        {
          "translations": [
            {
              "lang": "FR",
              "value": "as pensé"
            },
            {
              "lang": "DZ",
              "value": "khamemti"
            }
          ],
          "gender": "F",
          "possession": "YOU",
          "singular": true
        },
        {
          "translations": [
            {
              "lang": "FR",
              "value": "a pensé"
            },
            {
              "lang": "DZ",
              "value": "khamet"
            }
          ],
          "gender": "F",
          "possession": "OTHER",
          "singular": true
        },
        {
          "translations": [
            {
              "lang": "FR",
              "value": "as pensé"
            },
            {
              "lang": "DZ",
              "value": "khamemt"
            }
          ],
          "gender": "M",
          "possession": "YOU",
          "singular": true
        },
        {
          "translations": [
            {
              "lang": "FR",
              "value": "ont pensé"
            },
            {
              "lang": "DZ",
              "value": "khammou"
            }
          ],
          "gender": "F",
          "possession": "OTHER",
          "singular": false
        }
      ],
      "tense": "PAST"
    },
    {
      "conjugations": [
        {
          "translations": [
            {
              "lang": "FR",
              "value": "pense"
            },
            {
              "lang": "DZ",
              "value": "nkhamou"
            }
          ],
          "gender": "X",
          "possession": "I",
          "singular": false
        },
        {
          "translations": [
            {
              "lang": "FR",
              "value": "pensez"
            },
            {
              "lang": "DZ",
              "value": "tkhamou"
            }
          ],
          "gender": "X",
          "possession": "YOU",
          "singular": false
        },
        {
          "translations": [
            {
              "lang": "FR",
              "value": "pensent"
            },
            {
              "lang": "DZ",
              "value": "ikhamou"
            }
          ],
          "gender": "F",
          "possession": "OTHER",
          "singular": false
        },
        {
          "translations": [
            {
              "lang": "FR",
              "value": "penses"
            },
            {
              "lang": "DZ",
              "value": "tkhamem"
            }
          ],
          "gender": "M",
          "possession": "YOU",
          "singular": true
        },
        {
          "translations": [
            {
              "lang": "FR",
              "value": "pensent"
            },
            {
              "lang": "DZ",
              "value": "ikhamou"
            }
          ],
          "gender": "M",
          "possession": "OTHER",
          "singular": false
        },
        {
          "translations": [
            {
              "lang": "FR",
              "value": "pense"
            },
            {
              "lang": "DZ",
              "value": "tkhamem"
            }
          ],
          "gender": "F",
          "possession": "OTHER",
          "singular": true
        },
        {
          "translations": [
            {
              "lang": "FR",
              "value": "pense"
            },
            {
              "lang": "DZ",
              "value": "ikhamem"
            }
          ],
          "gender": "M",
          "possession": "OTHER",
          "singular": true
        },
        {
          "translations": [
            {
              "lang": "FR",
              "value": "pense"
            },
            {
              "lang": "DZ",
              "value": "nkhamem"
            }
          ],
          "gender": "X",
          "possession": "I",
          "singular": true
        },
        {
          "translations": [
            {
              "lang": "FR",
              "value": "penses"
            },
            {
              "lang": "DZ",
              "value": "tkhammi"
            }
          ],
          "gender": "F",
          "possession": "YOU",
          "singular": true
        }
      ],
      "tense": "PRESENT"
    }
  ],
  "word_type": "VERB",
  "possible_questions": [
  ],
  "possible_complements": [],
  "verb_type": "ACTION",
  "reflexive_suffix_fr": null,
  "reflexive_suffix_dz": null
}
